evonik/test/__init__.py
evonik/test/crudl/__init__.py
evonik/test/crudl/component.py
evonik/test/crudl/endpoint.py
evonik/test/crudl/instance.py
evonik/test/crudl/test_all.py
evonik/test/crudl/tests.py
evonik_test_crudl-0.0.5.dist-info/LICENSE
evonik_test_crudl-0.0.5.dist-info/METADATA
evonik_test_crudl-0.0.5.dist-info/WHEEL
evonik_test_crudl-0.0.5.dist-info/top_level.txt
evonik_test_crudl-0.0.5.dist-info/RECORD
