Metadata-Version: 2.1
Name: evonik-test-crudl
Version: 0.0.5
Summary: Helpers for testing CRUDL-like APIs, e.g., REST and GQL
Home-page: https://evodl.visualstudio.com/evonik-test-crudl
Author: Benjamin Schiller
Author-email: benjamin.schiller@evonik.com
License: UNKNOWN
Platform: UNKNOWN
Classifier: Programming Language :: Python :: 3
Classifier: License :: OSI Approved :: MIT License
Classifier: Operating System :: OS Independent
Requires-Python: >=3.7
Requires-Dist: evonik-dummy (>=0.0.12)
Requires-Dist: pytest (>=6.0.1)
